LICENSE
MANIFEST.in
README.md
setup.cfg
setup.py
versioneer.py
./.gitattributes
./CODE_OF_CONDUCT.md
./CONTRIBUTING.md
./LICENSE
./MANIFEST.in
./README.md
./setup.cfg
./setup.py
./versioneer.py
./addetect/__init__.py
./addetect/_version.py
./addetect/detector.py
./addetect.egg-info/PKG-INFO
./addetect.egg-info/SOURCES.txt
./addetect.egg-info/dependency_links.txt
./addetect.egg-info/requires.txt
./addetect.egg-info/top_level.txt
./tests/__init__.py
./tests/conftest.py
./tests/test_addetect.py
addetect/__init__.py
addetect/_version.py
addetect/detector.py
addetect.egg-info/PKG-INFO
addetect.egg-info/SOURCES.txt
addetect.egg-info/dependency_links.txt
addetect.egg-info/requires.txt
addetect.egg-info/top_level.txt
tests/__init__.py
tests/conftest.py
tests/test_addetect.py