Metadata-Version: 2.1
Name: addetect
Version: 0.1.28
Summary: A template for public packages, implementing the notion of compex number
Home-page: https://github.com/Advestis/addetect
Author: Advestis
Author-email: pythondev@advestis.com
License: GPLv3
Project-URL: Bug Tracker, https://github.com/Advestis/addetect/issues
Project-URL: Documentation, https://advestis.github.io/addetect
Project-URL: Source Code, https://github.com/Advestis/addetect/
Platform: UNKNOWN
Classifier: Development Status :: 5 - Production/Stable
Classifier: License :: OSI Approved :: GNU General Public License v3 (GPLv3)
Classifier: Operating System :: Unix
Classifier: Programming Language :: Python :: 3.7
Classifier: Programming Language :: Python :: 3.8
Classifier: Programming Language :: Python :: 3.9
Requires-Python: >=3.7
License-File: LICENSE
